geraci/__init__.py
geraci/core.py
geraci-1.0.0.dist-info/METADATA
geraci-1.0.0.dist-info/WHEEL
geraci-1.0.0.dist-info/top_level.txt
geraci-1.0.0.dist-info/RECORD
