Metadata-Version: 2.4
Name: geraci
Version: 1.0.0
Summary: A library for managing files and directories easily and efficiently.
Home-page: 
Author: Rpx
Author-email: cubyc.ro@gmail.com
License: MIT
Classifier: Programming Language :: Python :: 3
Classifier: Operating System :: OS Independent
Requires-Python: >=3.6
Dynamic: author
Dynamic: author-email
Dynamic: classifier
Dynamic: description
Dynamic: description-content-type
Dynamic: license
Dynamic: requires-python
Dynamic: summary
